{
  "id": "troika",
  "title": "Troika!",
  "description": "The official Foundry system for Troika! RPG",
  "url": "https://github.com/cussa/fvtt-troika",
  "license": "LICENSE.txt",
  "background": "systems/troika/assets/troika-compatibility-logo-splash-page.webp",
  "authors": [
    {
      "name": "Cussa Mitre",
      "url": "https://github.com/Cussa",
      "discord": "CussaMitre"
    },
    {
      "name": "N. Eimers",
      "discord": "TheLastScrub#7146"
    }    
  ],
  "version": "1.3.0",
  "compatibility": {
    "minimum": "11",
    "verified": "11"
  },
  "manifest": "https://github.com/cussa/fvtt-troika/releases/latest/download/system.json",
  "download": "https://github.com/cussa/fvtt-troika/releases/latest/download/system.zip",
  "gridDistance": 1,
  "gridUnits": "m",
  "primaryTokenAttribute": "stamina",
  "secondaryTokenAttribute": "luck",
  "esmodules": [
    "module/troika.js"
  ],
  "styles": [
    "css/troika.css"
  ],
  "languages": [
  ],
  "packs": [
    {
      "name": "troika-srd-spells",
      "label": "Troika SRD Spells",
      "system": "troika",
      "path": "packs/troika-srd-spells",
      "private": false,
      "type": "Item",
      "flags": {}
    },
    {
      "name": "troika-srd-roll-tables",
      "label": "Troika SRD Roll Tables",
      "system": "troika",
      "path": "packs/troika-srd-roll-tables",
      "private": false,
      "type": "RollTable",
      "flags": {}
    },
    {
      "name": "troika-srd-weapons",
      "label": "Troika SRD Weapons and Attacks",
      "system": "troika",
      "path": "packs/troika-srd-weapons-and-attacks",
      "private": false,
      "type": "Item",
      "flags": {}
    },
    {
      "name": "troika-srd-skills",
      "label": "Troika SRD Skills",
      "system": "troika",
      "path": "packs/troika-srd-skills",
      "private": false,
      "type": "Item",
      "flags": {}
    },
    {
      "name": "troika-srd-items",
      "label": "Troika SRD Items",
      "system": "troika",
      "path": "packs/troika-srd-items",
      "private": false,
      "type": "Item",
      "flags": {}
    },
    {
      "name": "troika-srd-backgrounds",
      "label": "Troika SRD Backgrounds",
      "system": "troika",
      "path": "packs/troika-srd-backgrounds",
      "private": false,
      "type": "Actor",
      "flags": {}
    }
  ],
  "flags": {
    "hotReload": {
      "extensions": ["css", "hbs", "json"],
      "paths": ["lang", "css", "templates"]
    }
  }
}