{
  "name": "True Seeing",
  "type": "spell",
  "img": "icons/svg/daze.svg",
  "system": {
    "name": "",
    "description": "<p><span dir=\"ltr\" role=\"presentation\">The wizard focuses their sight on the unambiguous truth of matter, </span><span dir=\"ltr\" role=\"presentation\">enabling them to see through illusions for the next 10 minutes.</span></p>",
    "attack": {
      "dr1": 2,
      "dr2": 2,
      "dr3": 2,
      "dr4": 2,
      "dr5": 4,
      "dr6": 8,
      "dr7": 10
    },
    "rank": "1",
    "castingCost": "3",
    "modifier": "0",
    "improvement": false,
    "canAttack": false
  },
  "effects": [],
  "flags": {},
  "_stats": {
    "systemId": "troika",
    "systemVersion": "0.2.7",
    "coreVersion": "10.291",
    "createdTime": 1676770922829,
    "modifiedTime": 1676771738846,
    "lastModifiedBy": "iubUFLpmPB0vkjXq"
  },
  "_id": "GwiaD3KNEX4BlQWQ",
  "folder": null,
  "sort": 0,
  "ownership": {
    "default": 0,
    "iubUFLpmPB0vkjXq": 3
  },
  "_key": "!items!GwiaD3KNEX4BlQWQ"
}
